hid_usb_relay/__init__.py
hid_usb_relay/app.py
hid_usb_relay/hid_usb_relay_bin/__init__.py
hid_usb_relay/hid_usb_relay_bin/linux/32bit/hidusb-relay-cmd
hid_usb_relay/hid_usb_relay_bin/linux/64bit/hidusb-relay-cmd
hid_usb_relay/hid_usb_relay_bin/windows/32bit/GUIapp.exe
hid_usb_relay/hid_usb_relay_bin/windows/32bit/USB_RELAY_DEVICE.dll
hid_usb_relay/hid_usb_relay_bin/windows/32bit/hidusb-relay-cmd.exe
hid_usb_relay/hid_usb_relay_bin/windows/64bit/GUIapp.exe
hid_usb_relay/hid_usb_relay_bin/windows/64bit/USB_RELAY_DEVICE.dll
hid_usb_relay/hid_usb_relay_bin/windows/64bit/hidusb-relay-cmd.exe
hid_usb_relay/usb_relay.py
hid_usb_relay-26.0.0.dist-info/WHEEL
hid_usb_relay-26.0.0.dist-info/METADATA
hid_usb_relay-26.0.0.dist-info/RECORD
