Metadata-Version: 2.3
Name: hid-usb-relay
Version: 26.0.0
Summary: hid based usb relay package
Keywords: Python,HID,USB,RELAY
Author: chaitu-ycr
Author-email: chaitu-ycr <chaitu.ycr@gmail.com>
License: MIT License
Classifier: Programming Language :: Python :: 3.10
Classifier: Programming Language :: Python :: 3.11
Classifier: Programming Language :: Python :: 3.12
Classifier: Programming Language :: Python :: 3.13
Classifier: Programming Language :: Python :: 3.14
Classifier: License :: OSI Approved :: MIT License
Classifier: Operating System :: Microsoft :: Windows
Classifier: Operating System :: POSIX :: Linux
Requires-Dist: nicegui[native]
Requires-Python: >=3.10, <=3.14
Project-URL: homepage, https://github.com/chaitu-ycr/hid-usb-relay
Project-URL: repository, https://github.com/chaitu-ycr/hid-usb-relay
Project-URL: documentation, https://chaitu-ycr.github.io/hid-usb-relay
